vlclient/__init__.py
vlclient/auth.py
vlclient/client.py
vlclient/exceptions.py
vlclient/resources.py
vlclient-1.0.1.dist-info/LICENSE
vlclient-1.0.1.dist-info/METADATA
vlclient-1.0.1.dist-info/WHEEL
vlclient-1.0.1.dist-info/RECORD
