Metadata-Version: 2.1
Name: vlclient
Version: 1.0.1
Summary: Valorant Client API Wrapper
Author: anntnzrb
Author-email: anntnzrb@proton.me
Requires-Python: >=3.11,<4.0
Classifier: Programming Language :: Python :: 3
Classifier: Programming Language :: Python :: 3.11
Requires-Dist: requests (>=2.31.0,<3.0.0)
